RNUMPY/__init__.py
RNUMPY/_basearrays.py
RNUMPY/reference_src.py
RNUMPY/src.py
RNUMPY/version.py
RNUMPY/lax/__init__.py
RNUMPY/lax/src.py
RNUMPY/linalg/__init__.py
RNUMPY/linalg/src.py
RNUMPY/scipy/__init__.py
RNUMPY/scipy/fft.py
RNUMPY/scipy/integrate.py
RNUMPY/scipy/interpolate.py
RNUMPY/scipy/linalg.py
RNUMPY/scipy/optimize.py
RNUMPY/scipy/signal.py
RNUMPY/scipy/special.py
RNUMPY/scipy/src.py
RNUMPY/scipy/sparse/__init__.py
RNUMPY/scipy/sparse/linalg.py
RNUMPY/scipy/spatial/__init__.py
RNUMPY/scipy/spatial/transform/Rotation.py
RNUMPY/scipy/spatial/transform/Slerp.py
RNUMPY/scipy/spatial/transform/__init__.py
rnp-0.1.0.dist-info/LICENSE
rnp-0.1.0.dist-info/METADATA
rnp-0.1.0.dist-info/WHEEL
rnp-0.1.0.dist-info/top_level.txt
rnp-0.1.0.dist-info/RECORD
