Metadata-Version: 2.1
Name: rnp
Version: 0.1.0
Summary: Research Numpy: run either JAX or standard Numpy from a common interface
Author: Aerospace Research Community Team
Maintainer: The Developers
License:                                  Apache License
Project-URL: Homepage, https://github.com/RCAIDE/RNUMPY
Project-URL: Issues, https://github.com/RCAIDE/RNUMPY/issues
Classifier: Programming Language :: Python :: 3
Classifier: Operating System :: OS Independent
Classifier: Development Status :: 4 - Beta
Requires-Python: >=3.10
License-File: LICENSE
Requires-Dist: numpy
Requires-Dist: scipy
